bs_python_utils/Timer.py
bs_python_utils/__init__.py
bs_python_utils/bivariate_quantiles.py
bs_python_utils/bs_altair.py
bs_python_utils/bs_logging.py
bs_python_utils/bs_mathstr.py
bs_python_utils/bs_mem.py
bs_python_utils/bs_opt.py
bs_python_utils/bs_plots.py
bs_python_utils/bs_seaborn.py
bs_python_utils/bs_sparse_gaussian.py
bs_python_utils/bsmplutils.py
bs_python_utils/bsnputils.py
bs_python_utils/bssputils.py
bs_python_utils/bsstats.py
bs_python_utils/bsutils.py
bs_python_utils/chebyshev.py
bs_python_utils/distance_covariances.py
bs_python_utils/pandas_utils.py
bs_python_utils/sklearn_utils.py
bs_python_utils/streamlit_utils.py
bs_python_utils/GaussHermiteSparseGrids/GHsparseGrid1prec13.txt
bs_python_utils/GaussHermiteSparseGrids/GHsparseGrid1prec17.txt
bs_python_utils/GaussHermiteSparseGrids/GHsparseGrid1prec9.txt
bs_python_utils/GaussHermiteSparseGrids/GHsparseGrid2prec13.txt
bs_python_utils/GaussHermiteSparseGrids/GHsparseGrid2prec17.txt
bs_python_utils/GaussHermiteSparseGrids/GHsparseGrid2prec9.txt
bs_python_utils/GaussHermiteSparseGrids/GHsparseGrid3prec13.txt
bs_python_utils/GaussHermiteSparseGrids/GHsparseGrid3prec17.txt
bs_python_utils/GaussHermiteSparseGrids/GHsparseGrid3prec9.txt
bs_python_utils/GaussHermiteSparseGrids/GHsparseGrid4prec13.txt
bs_python_utils/GaussHermiteSparseGrids/GHsparseGrid4prec17.txt
bs_python_utils/GaussHermiteSparseGrids/GHsparseGrid4prec9.txt
bs_python_utils/GaussHermiteSparseGrids/GHsparseGrid5prec13.txt
bs_python_utils/GaussHermiteSparseGrids/GHsparseGrid5prec17.txt
bs_python_utils/GaussHermiteSparseGrids/GHsparseGrid5prec9.txt
bs_python_utils/examples/examples_altair.py
bs_python_utils/examples/examples_distance_covariances.py
bs_python_utils/examples/examples_mem.py
bs_python_utils/examples/examples_mpl.py
bs_python_utils/examples/examples_opt.py
bs_python_utils/examples/examples_seaborn.py
bs_python_utils/examples/examples_sklearn.py
bs_python_utils/examples/examples_sparse_gaussian.py
bs_python_utils-0.8.5.dist-info/licenses/LICENSE
bs_python_utils-0.8.5.dist-info/METADATA
bs_python_utils-0.8.5.dist-info/WHEEL
bs_python_utils-0.8.5.dist-info/top_level.txt
bs_python_utils-0.8.5.dist-info/RECORD
