Metadata-Version: 2.4
Name: bs-python-utils
Version: 0.8.5
Summary: Utilities programs for my Python code
Requires-Python: >=3.12
License-File: LICENSE
Requires-Dist: altair>=5.5.0
Requires-Dist: altair-saver>=0.5.0
Requires-Dist: emcee>=3.1.6
Requires-Dist: matplotlib>=3.10.6
Requires-Dist: mkdocs>=1.6.1
Requires-Dist: mkdocs-material>=9.6.20
Requires-Dist: mkdocstrings-python>=1.18.2
Requires-Dist: numpy>=2.3.3
Requires-Dist: pandas>=2.3.2
Requires-Dist: pre-commit>=4.3.0
Requires-Dist: pytest>=8.4.2
Requires-Dist: mypy
Requires-Dist: ruff>=0.14.0
Requires-Dist: scikit-learn>=1.7.2
Requires-Dist: scipy>=1.16.2
Requires-Dist: seaborn>=0.13.2
Requires-Dist: statsmodels>=0.14.5
Requires-Dist: streamlit>=1.49.1
Requires-Dist: vega-datasets>=0.9.0
Requires-Dist: colorama>=0.4.6
Dynamic: license-file
